python_bedrock/__init__.py
python_bedrock/auth/login.py
python_bedrock/auth/security.py
python_bedrock/auth/xbox.py
python_bedrock/auth.py
python_bedrock/client.py
python_bedrock/connection.py
python_bedrock/createClient.py
python_bedrock/createServer.py
python_bedrock/datatypes/__init__.py
python_bedrock/datatypes/handshake.py
python_bedrock/datatypes/minecraft.py
python_bedrock/datatypes/packets.py
python_bedrock/datatypes/protocol.py
python_bedrock/datatypes/resources.py
python_bedrock/datatypes/util.py
python_bedrock/encryption.py
python_bedrock/handshake/__init__.py
python_bedrock/handshake/keyExchange.py
python_bedrock/handshake/login.py
python_bedrock/logging.py
python_bedrock/ping.py
python_bedrock/protocol/batching.py
python_bedrock/protocol/compression.py
python_bedrock/protocol/entities.py
python_bedrock/protocol/inventory.py
python_bedrock/protocol/logging.py
python_bedrock/protocol/nbt.py
python_bedrock/protocol/packets.py
python_bedrock/protocol/types.py
python_bedrock/protocol/versions.py
python_bedrock/raknet/client.py
python_bedrock/raknet/datagrams.py
python_bedrock/raknet/protocol.py
python_bedrock/raknet/server.py
python_bedrock/server.py
python_bedrock/transforms/__init__.py
python_bedrock/transforms/framer.py
python_bedrock/transforms/serializer.py
python_bedrock/types.py
python_bedrock-1.1.1.dist-info/METADATA
python_bedrock-1.1.1.dist-info/WHEEL
python_bedrock-1.1.1.dist-info/licenses/LICENSE
python_bedrock-1.1.1.dist-info/RECORD
