Metadata-Version: 2.4
Name: python-bedrock
Version: 1.1.1
Summary: Async Python reimplementation of the Bedrock protocol.
License: MIT
License-File: LICENSE
Keywords: minecraft,bedrock,protocol,async
Author: ghulq
Requires-Python: >=3.9
Classifier: Development Status :: 3 - Alpha
Classifier: Intended Audience :: Developers
Classifier: Topic :: Software Development :: Libraries :: Python Modules
Classifier: License :: OSI Approved :: MIT License
Classifier: Programming Language :: Python :: 3
Classifier: Programming Language :: Python :: 3.9
Classifier: Programming Language :: Python :: 3.10
Classifier: Programming Language :: Python :: 3.11
Classifier: Operating System :: OS Independent
Requires-Dist: aiohttp (>=3.8)
Requires-Dist: cryptography (>=3.4)
Requires-Dist: pyjwt (>=2.10.1)
Project-URL: Bug Tracker, https://github.com/ghulq/python-bedrock/issues
Project-URL: Documentation, https://github.com/ghulq/python-bedrock#readme
Project-URL: Homepage, https://github.com/ghulq/python-bedrock
Project-URL: Source, https://github.com/ghulq/python-bedrock
